pyspark_testframework-3.0.0.dist-info/licenses/LICENSE
testframework/__init__.py
testframework/_version.py
testframework/dataquality/__init__.py
testframework/dataquality/_base.py
testframework/dataquality/dataframe/__init__.py
testframework/dataquality/dataframe/dataframe_tester.py
testframework/dataquality/tests/__init__.py
testframework/dataquality/tests/correct_value.py
testframework/dataquality/tests/integer_string.py
testframework/dataquality/tests/not_null.py
testframework/dataquality/tests/regex_tst.py
testframework/dataquality/tests/valid_category.py
testframework/dataquality/tests/valid_date_range.py
testframework/dataquality/tests/valid_email_address.py
testframework/dataquality/tests/valid_numeric_range.py
testframework/dataquality/tests/valid_numeric_string_range.py
testframework/dataquality/tests/valid_string_length.py
testframework/utils/__init__.py
testframework/utils/decorators.py
pyspark_testframework-3.0.0.dist-info/METADATA
pyspark_testframework-3.0.0.dist-info/WHEEL
pyspark_testframework-3.0.0.dist-info/top_level.txt
pyspark_testframework-3.0.0.dist-info/RECORD
