Metadata-Version: 2.4
Name: pyspark-testframework
Version: 3.0.0
Summary: Testframework for PySpark DataFrames
Author-email: Woonstad Rotterdam <info@woonstadrotterdam.nl>, Tomer Gabay <tomer.gabay@woonstadrotterdam.nl>, Vincent van der Meij <vincent.van.der.meij@woonstadrotterdam.nl>, Tiddo Loos <tiddo.loos@woonstadrotterdam.nl>, Ben Verhees <ben.verhees@woonstadrotterdam.nl>
License: MIT License
Project-URL: Homepage, https://github.com/woonstadrotterdam/pyspark-testframework
Project-URL: Issues, https://github.com/woonstadrotterdam/pyspark-testframework/issues
Keywords: pyspark,dataframe,test,testframework
Classifier: Programming Language :: Python :: 3.9
Classifier: Programming Language :: Python :: 3.10
Classifier: Programming Language :: Python :: 3.11
Classifier: Programming Language :: Python :: 3.12
Classifier: License :: OSI Approved :: MIT License
Classifier: Operating System :: OS Independent
Requires-Python: >=3.9.5
License-File: LICENSE
Provides-Extra: test
Requires-Dist: pre-commit==3.*; extra == "test"
Requires-Dist: pytest==8.*; extra == "test"
Requires-Dist: pytest-cov==5.*; extra == "test"
Requires-Dist: pyspark==3.*; extra == "test"
Provides-Extra: dev
Requires-Dist: pyspark-testframework[test]; extra == "dev"
Requires-Dist: ruff==0.4.8; extra == "dev"
Dynamic: license-file
